Metadata-Version: 2.1
Name: egrabber
Version: 0.0.2
Summary: testpack
Home-page: UNKNOWN
Author: hari
Author-email: hari@example.com
License: UNKNOWN
Platform: UNKNOWN
Classifier: Programming Language :: Python :: 3
Classifier: License :: OSI Approved :: MIT License
Classifier: Operating System :: OS Independent
